[{"usuario":"leonel1988","email":"leo@gmail.com","contrasenia":"$2y$10$dSKZ6KJZcXRk7aA8GWHaUe8uxFQ3lCepodsl8VTyZ4L4O\/6XfdWqu"},{"usuario":"sara_1989","email":"sara@gmail.com","contrasenia":"$2y$10$3j1tVotPUz84qFKKdaG4BeTYumLxZ5Z9.uMtfL4IS3jXeb\/yP5blC"},{"usuario":"leo_laz33","email":"leonel@gmail.com","contrasenia":"$2y$10$JP890Uolli8Xb\/c\/kAjP0u\/vjwFL.icj0YrsYoA6uY0NgBGpKTC8C"},{"usuario":"leo_3_lazcano","email":"lazcano@gmail.com","contrasenia":"$2y$10$KG6ttCS5yMm4r2NY0Cyr\/eJk.eXnF447vQLgGgbOi\/ofl1.E3z60S"},{"usuario":"lazcano1988","email":"lazcanoleonel@gmail.com","contrasenia":"$2y$10$6X..jnH04foqsUEKn5pLQ.GmdjK7Nx.6AWvFEBuLWLUeuB8MypO\/q"},{"usuario":"leosara1988","email":"leosara@gmail.com","contrasenia":"$2y$10$eORmv0FhhUltocT8PJLsNORQhlRe49cewa31YVhf4ZjVT96psXBbq"}]
